wintersong/__about__.py
wintersong/__init__.py
wintersong/base.html
wintersong/icon.png
wintersong/main.html
wintersong/meta.html
wintersong/mkdocs_theme.yml
wintersong/winter.css
wintersong/winter.css.map
wintersong/winter.js
wintersong/winter.js.map
wintersong/winterbloom.png
wintersong-2024.9.8.dist-info/METADATA
wintersong-2024.9.8.dist-info/WHEEL
wintersong-2024.9.8.dist-info/entry_points.txt
wintersong-2024.9.8.dist-info/licenses/LICENSE
wintersong-2024.9.8.dist-info/RECORD
