Metadata-Version: 2.3
Name: wintersong
Version: 2024.9.8
Project-URL: Documentation, https://github.com/wntrblm/wintersong#readme
Project-URL: Issues, https://github.com/wntrblm/wintersong/issues
Project-URL: Source, https://github.com/wntrblm/wintersong
Author-email: Thea Flowers <thea@winterbloom.com>
License: Wintersong is copyright (c) 2021 Alethea Katherine Flowers / Winterbloom
License-File: LICENSE
Keywords: mkdocs,theme
Classifier: Programming Language :: Python
Classifier: Programming Language :: Python :: 3.12
Classifier: Programming Language :: Python :: Implementation :: CPython
Requires-Python: >=3.12
Requires-Dist: mkdocs>=1.5.0
Requires-Dist: pygments>=2.16
Requires-Dist: pymdown-extensions>=10.3
